nornsible/__init__.py
nornsible/cli.py
nornsible/decorators.py
nornsible/functions.py
nornsible/inventory.py
nornsible/nornsible.py
nornsible-2020.1.11.dist-info/LICENSE
nornsible-2020.1.11.dist-info/METADATA
nornsible-2020.1.11.dist-info/WHEEL
nornsible-2020.1.11.dist-info/top_level.txt
nornsible-2020.1.11.dist-info/RECORD
