Metadata-Version: 2.1
Name: nornsible
Version: 2020.1.11
Summary: Ansible-like inventory utility for Nornir.
Home-page: UNKNOWN
Author: Carl Montanari
Author-email: carl.r.montanari@gmail.com
License: UNKNOWN
Platform: UNKNOWN
Classifier: License :: OSI Approved :: MIT License
Classifier: Programming Language :: Python :: 3
Classifier: Programming Language :: Python :: 3.6
Classifier: Programming Language :: Python :: 3.7
Classifier: Programming Language :: Python :: 3.8
Classifier: Operating System :: POSIX :: Linux
Classifier: Operating System :: MacOS
Requires-Python: >=3.6
Requires-Dist: colorama (>=0.3.9)
Requires-Dist: nornir (>=2.2.0)
